{
  "C101_C101_2dd87652bc8a448bb1d1221a9b0f3028.mov": {
    "classId": "C101",
    "video_id": "C101_2dd87652bc8a448bb1d1221a9b0f3028.mov",
    "students": []
  },
  "C101_C101_01e9efe9dab94c30af553c50e360e74b.mov": {
    "classId": "C101",
    "video_id": "C101_01e9efe9dab94c30af553c50e360e74b.mov",
    "students": [
      {
        "cluster_id": 0,
        "name": "Sagnik",
        "roll_no": "123"
      },
      {
        "cluster_id": 1,
        "name": "",
        "roll_no": ""
      },
      {
        "cluster_id": 2,
        "name": "",
        "roll_no": ""
      },
      {
        "cluster_id": 3,
        "name": "",
        "roll_no": ""
      },
      {
        "cluster_id": 4,
        "name": "",
        "roll_no": ""
      },
      {
        "cluster_id": 5,
        "name": "",
        "roll_no": ""
      },
      {
        "cluster_id": 6,
        "name": "",
        "roll_no": ""
      },
      {
        "cluster_id": 7,
        "name": "",
        "roll_no": ""
      },
      {
        "cluster_id": 8,
        "name": "",
        "roll_no": ""
      },
      {
        "cluster_id": 9,
        "name": "",
        "roll_no": ""
      },
      {
        "cluster_id": 10,
        "name": "",
        "roll_no": ""
      },
      {
        "cluster_id": 11,
        "name": "",
        "roll_no": ""
      },
      {
        "cluster_id": 12,
        "name": "",
        "roll_no": ""
      },
      {
        "cluster_id": 13,
        "name": "",
        "roll_no": ""
      },
      {
        "cluster_id": 14,
        "name": "",
        "roll_no": ""
      },
      {
        "cluster_id": 15,
        "name": "",
        "roll_no": ""
      },
      {
        "cluster_id": 16,
        "name": "",
        "roll_no": ""
      },
      {
        "cluster_id": 17,
        "name": "",
        "roll_no": ""
      },
      {
        "cluster_id": 18,
        "name": "",
        "roll_no": ""
      },
      {
        "cluster_id": 19,
        "name": "",
        "roll_no": ""
      },
      {
        "cluster_id": 20,
        "name": "",
        "roll_no": ""
      },
      {
        "cluster_id": 21,
        "name": "",
        "roll_no": ""
      },
      {
        "cluster_id": 22,
        "name": "",
        "roll_no": ""
      },
      {
        "cluster_id": 23,
        "name": "",
        "roll_no": ""
      },
      {
        "cluster_id": 24,
        "name": "",
        "roll_no": ""
      },
      {
        "cluster_id": 25,
        "name": "",
        "roll_no": ""
      },
      {
        "cluster_id": 26,
        "name": "",
        "roll_no": ""
      },
      {
        "cluster_id": 27,
        "name": "",
        "roll_no": ""
      },
      {
        "cluster_id": 28,
        "name": "",
        "roll_no": ""
      },
      {
        "cluster_id": 29,
        "name": "",
        "roll_no": ""
      },
      {
        "cluster_id": 30,
        "name": "",
        "roll_no": ""
      },
      {
        "cluster_id": 31,
        "name": "",
        "roll_no": ""
      },
      {
        "cluster_id": 32,
        "name": "",
        "roll_no": ""
      },
      {
        "cluster_id": 33,
        "name": "",
        "roll_no": ""
      },
      {
        "cluster_id": 34,
        "name": "",
        "roll_no": ""
      },
      {
        "cluster_id": 35,
        "name": "",
        "roll_no": ""
      },
      {
        "cluster_id": 36,
        "name": "",
        "roll_no": ""
      },
      {
        "cluster_id": 37,
        "name": "",
        "roll_no": ""
      },
      {
        "cluster_id": 38,
        "name": "",
        "roll_no": ""
      },
      {
        "cluster_id": 39,
        "name": "",
        "roll_no": ""
      },
      {
        "cluster_id": 40,
        "name": "",
        "roll_no": ""
      },
      {
        "cluster_id": 41,
        "name": "",
        "roll_no": ""
      },
      {
        "cluster_id": 42,
        "name": "",
        "roll_no": ""
      },
      {
        "cluster_id": 43,
        "name": "",
        "roll_no": ""
      },
      {
        "cluster_id": 44,
        "name": "",
        "roll_no": ""
      },
      {
        "cluster_id": 45,
        "name": "",
        "roll_no": ""
      },
      {
        "cluster_id": 46,
        "name": "",
        "roll_no": ""
      },
      {
        "cluster_id": 47,
        "name": "",
        "roll_no": ""
      },
      {
        "cluster_id": 48,
        "name": "",
        "roll_no": ""
      },
      {
        "cluster_id": 49,
        "name": "",
        "roll_no": ""
      },
      {
        "cluster_id": 50,
        "name": "",
        "roll_no": ""
      },
      {
        "cluster_id": 51,
        "name": "",
        "roll_no": ""
      },
      {
        "cluster_id": 52,
        "name": "",
        "roll_no": ""
      },
      {
        "cluster_id": 53,
        "name": "",
        "roll_no": ""
      },
      {
        "cluster_id": 54,
        "name": "",
        "roll_no": ""
      },
      {
        "cluster_id": 55,
        "name": "",
        "roll_no": ""
      },
      {
        "cluster_id": 56,
        "name": "",
        "roll_no": ""
      },
      {
        "cluster_id": 57,
        "name": "",
        "roll_no": ""
      },
      {
        "cluster_id": 58,
        "name": "",
        "roll_no": ""
      },
      {
        "cluster_id": 59,
        "name": "",
        "roll_no": ""
      },
      {
        "cluster_id": 60,
        "name": "",
        "roll_no": ""
      },
      {
        "cluster_id": 61,
        "name": "",
        "roll_no": ""
      },
      {
        "cluster_id": 62,
        "name": "",
        "roll_no": ""
      },
      {
        "cluster_id": 63,
        "name": "",
        "roll_no": ""
      },
      {
        "cluster_id": 64,
        "name": "",
        "roll_no": ""
      },
      {
        "cluster_id": 65,
        "name": "",
        "roll_no": ""
      },
      {
        "cluster_id": 66,
        "name": "",
        "roll_no": ""
      },
      {
        "cluster_id": 67,
        "name": "",
        "roll_no": ""
      },
      {
        "cluster_id": 68,
        "name": "",
        "roll_no": ""
      },
      {
        "cluster_id": 69,
        "name": "",
        "roll_no": ""
      },
      {
        "cluster_id": 70,
        "name": "",
        "roll_no": ""
      },
      {
        "cluster_id": 71,
        "name": "",
        "roll_no": ""
      },
      {
        "cluster_id": 72,
        "name": "",
        "roll_no": ""
      },
      {
        "cluster_id": 73,
        "name": "",
        "roll_no": ""
      }
    ]
  }
}